amendment_forecast/__init__.py
amendment_forecast/main.py
amendment_forecast/models.py
amendment_forecast/utils.py
amendment_forecast-1.5.4.dist-info/METADATA
amendment_forecast-1.5.4.dist-info/WHEEL
amendment_forecast-1.5.4.dist-info/top_level.txt
amendment_forecast-1.5.4.dist-info/RECORD
