Metadata-Version: 2.1
Name: amendment_forecast
Version: 1.5.4
Summary: A forecaster for sales data
Home-page: https://github.com/amendmentai/forecast_models
Author: Makani Cartwright
Author-email: makani@amendmentai.com
Classifier: Programming Language :: Python :: 3
Classifier: Operating System :: OS Independent
Requires-Python: >=3.6
